packages/__init__.py
packages/gen.py
packages/group.py
packages/j.py
tests/__init__.py
tests/conftest.py
tests/test_feature.py
simple_gen-2020.1.13.dist-info/METADATA
simple_gen-2020.1.13.dist-info/WHEEL
simple_gen-2020.1.13.dist-info/entry_points.txt
simple_gen-2020.1.13.dist-info/top_level.txt
simple_gen-2020.1.13.dist-info/RECORD
