Metadata-Version: 2.1
Name: simple-gen
Version: 2020.1.13
Summary: gen files
Home-page: UNKNOWN
Author: buglan
Author-email: 1831353087@qq.com
License: UNKNOWN
Platform: UNKNOWN
Requires-Dist: click
Requires-Dist: PyJWT
